{
    "total": [
        {
            "id": "100071768980176",
            "count": 15
        },
        {
            "id": "100029340348630",
            "count": 0
        },
        {
            "id": "100078770982954",
            "count": 8
        },
        {
            "id": "100093012078559",
            "count": 0
        },
        {
            "id": "100028201899374",
            "count": 24
        },
        {
            "id": "100071216006358",
            "count": 3
        },
        {
            "id": "100089033040313",
            "count": 2
        },
        {
            "id": "100087986034465",
            "count": 0
        },
        {
            "id": "100088810007933",
            "count": 2
        },
        {
            "id": "100060845223319",
            "count": 0
        },
        {
            "id": "100080127415127",
            "count": 0
        },
        {
            "id": "100056967003808",
            "count": 2
        },
        {
            "id": "100090436251497",
            "count": 0
        },
        {
            "id": "61559179119012",
            "count": 0
        },
        {
            "id": "100062327635551",
            "count": 0
        },
        {
            "id": "61552955900740",
            "count": 0
        },
        {
            "id": "100086649001317",
            "count": 0
        },
        {
            "id": "100005375501114",
            "count": 0
        },
        {
            "id": "100075683151810",
            "count": 0
        },
        {
            "id": "100029319195167",
            "count": 9
        },
        {
            "id": "100040542224086",
            "count": 0
        },
        {
            "id": "100078831493987",
            "count": 21
        },
        {
            "id": "100002486883891",
            "count": 0
        },
        {
            "id": "100089195796584",
            "count": 0
        },
        {
            "id": "100080101487002",
            "count": 0
        },
        {
            "id": "666896678",
            "count": 20
        },
        {
            "id": "100039603168929",
            "count": 0
        },
        {
            "id": "100016874224065",
            "count": 1
        },
        {
            "id": "100083174347639",
            "count": 15
        },
        {
            "id": "100071680238906",
            "count": 0
        },
        {
            "id": "100056903295591",
            "count": 54
        },
        {
            "id": "100023947532213",
            "count": 0
        },
        {
            "id": "100026180030782",
            "count": 0
        },
        {
            "id": "1550702797",
            "count": 22
        },
        {
            "id": "61563772222586",
            "count": 20
        },
        {
            "id": "61561974429884",
            "count": 0
        },
        {
            "id": "100076900489677",
            "count": 48
        },
        {
            "id": "100001283010247",
            "count": 12
        },
        {
            "id": "61559047337017",
            "count": 0
        },
        {
            "id": "100007621141247",
            "count": 1
        },
        {
            "id": "61564147886146",
            "count": 13
        },
        {
            "id": "1721994577",
            "count": 10
        },
        {
            "id": "100085462005868",
            "count": 0
        }
    ],
    "week": [
        {
            "id": "100071768980176",
            "count": 0,
            "name": "Hoàng Xuân Thành ✓"
        },
        {
            "id": "100029340348630",
            "count": 0,
            "name": "Người dùng facebook"
        },
        {
            "id": "100078770982954",
            "count": 0,
            "name": "Người dùng facebook"
        },
        {
            "id": "100093012078559",
            "count": 0,
            "name": "Người dùng facebook"
        },
        {
            "id": "100028201899374",
            "count": 0,
            "name": "Người dùng facebook"
        },
        {
            "id": "100071216006358",
            "count": 0,
            "name": "Người dùng facebook"
        },
        {
            "id": "100089033040313",
            "count": 0,
            "name": "Nguyễn Đức Toàn"
        },
        {
            "id": "100087986034465",
            "count": 0,
            "name": "Lê Thị Thảo Hương"
        },
        {
            "id": "100088810007933",
            "count": 0,
            "name": "Người dùng facebook"
        },
        {
            "id": "100060845223319",
            "count": 0,
            "name": "Người dùng facebook"
        },
        {
            "id": "100080127415127",
            "count": 0,
            "name": "Người dùng facebook"
        },
        {
            "id": "100056967003808",
            "count": 0,
            "name": "Người dùng facebook"
        },
        {
            "id": "100090436251497",
            "count": 0,
            "name": "Người dùng facebook"
        },
        {
            "id": "61559179119012",
            "count": 0,
            "name": "Người dùng facebook"
        },
        {
            "id": "100062327635551",
            "count": 0,
            "name": "Người dùng facebook"
        },
        {
            "id": "61552955900740",
            "count": 0,
            "name": "Thương Em"
        },
        {
            "id": "100086649001317",
            "count": 0,
            "name": "Ken Cần Cù"
        },
        {
            "id": "100005375501114",
            "count": 0,
            "name": "Người dùng facebook"
        },
        {
            "id": "100075683151810",
            "count": 0,
            "name": "Người dùng facebook"
        },
        {
            "id": "100029319195167",
            "count": 0,
            "name": "Người dùng facebook"
        },
        {
            "id": "100040542224086",
            "count": 0,
            "name": "Ah Quân"
        },
        {
            "id": "100078831493987",
            "count": 0,
            "name": "Người dùng facebook"
        },
        {
            "id": "100002486883891",
            "count": 0,
            "name": "Người dùng facebook"
        },
        {
            "id": "100089195796584",
            "count": 0,
            "name": "Dũng Nguyễn"
        },
        {
            "id": "100080101487002",
            "count": 0,
            "name": "Mẫn Nhi"
        },
        {
            "id": "666896678",
            "count": 0,
            "name": "Ah Ko Thích"
        },
        {
            "id": "100039603168929",
            "count": 0,
            "name": "Người dùng facebook"
        },
        {
            "id": "100016874224065",
            "count": 0,
            "name": "Người dùng facebook"
        },
        {
            "id": "100083174347639",
            "count": 0,
            "name": "Nguyễn Đức Bình✅"
        },
        {
            "id": "100071680238906",
            "count": 0,
            "name": "Người dùng facebook"
        },
        {
            "id": "100056903295591",
            "count": 0,
            "name": "Người dùng facebook"
        },
        {
            "id": "100023947532213",
            "count": 0,
            "name": "Người dùng facebook"
        },
        {
            "id": "100026180030782",
            "count": 0,
            "name": "Người dùng facebook"
        },
        {
            "id": "1550702797",
            "count": 0,
            "name": "Người dùng facebook"
        },
        {
            "id": "61563772222586",
            "count": 0,
            "name": "Người dùng facebook"
        },
        {
            "id": "61561974429884",
            "count": 0,
            "name": "Người dùng facebook"
        },
        {
            "id": "100076900489677",
            "count": 0,
            "name": "Lê Yến Nhi"
        },
        {
            "id": "100001283010247",
            "count": 0,
            "name": "Người dùng facebook"
        },
        {
            "id": "61559047337017",
            "count": 0,
            "name": "Người dùng facebook"
        },
        {
            "id": "100007621141247",
            "count": 0,
            "name": "Người dùng facebook"
        },
        {
            "id": "61564147886146",
            "count": 0,
            "name": "Người dùng facebook"
        },
        {
            "id": "1721994577",
            "count": 0,
            "name": "Người dùng facebook"
        },
        {
            "id": "100085462005868",
            "count": 0,
            "name": "Người dùng facebook"
        }
    ],
    "day": [
        {
            "id": "100071768980176",
            "count": 0,
            "name": "Hoàng Xuân Thành ✓"
        },
        {
            "id": "100029340348630",
            "count": 0,
            "name": "Người dùng facebook"
        },
        {
            "id": "100078770982954",
            "count": 0,
            "name": "Người dùng facebook"
        },
        {
            "id": "100093012078559",
            "count": 0,
            "name": "Người dùng facebook"
        },
        {
            "id": "100028201899374",
            "count": 0,
            "name": "Người dùng facebook"
        },
        {
            "id": "100071216006358",
            "count": 0,
            "name": "Người dùng facebook"
        },
        {
            "id": "100089033040313",
            "count": 0,
            "name": "Nguyễn Đức Toàn"
        },
        {
            "id": "100087986034465",
            "count": 0,
            "name": "Lê Thị Thảo Hương"
        },
        {
            "id": "100088810007933",
            "count": 0,
            "name": "Người dùng facebook"
        },
        {
            "id": "100060845223319",
            "count": 0,
            "name": "Người dùng facebook"
        },
        {
            "id": "100080127415127",
            "count": 0,
            "name": "Người dùng facebook"
        },
        {
            "id": "100056967003808",
            "count": 0,
            "name": "Người dùng facebook"
        },
        {
            "id": "100090436251497",
            "count": 0,
            "name": "Người dùng facebook"
        },
        {
            "id": "61559179119012",
            "count": 0,
            "name": "Người dùng facebook"
        },
        {
            "id": "100062327635551",
            "count": 0,
            "name": "Người dùng facebook"
        },
        {
            "id": "61552955900740",
            "count": 0,
            "name": "Thương Em"
        },
        {
            "id": "100086649001317",
            "count": 0,
            "name": "Ken Cần Cù"
        },
        {
            "id": "100005375501114",
            "count": 0,
            "name": "Người dùng facebook"
        },
        {
            "id": "100075683151810",
            "count": 0,
            "name": "Người dùng facebook"
        },
        {
            "id": "100029319195167",
            "count": 0,
            "name": "Người dùng facebook"
        },
        {
            "id": "100040542224086",
            "count": 0,
            "name": "Ah Quân"
        },
        {
            "id": "100078831493987",
            "count": 0,
            "name": "Người dùng facebook"
        },
        {
            "id": "100002486883891",
            "count": 0,
            "name": "Người dùng facebook"
        },
        {
            "id": "100089195796584",
            "count": 0,
            "name": "Dũng Nguyễn"
        },
        {
            "id": "100080101487002",
            "count": 0,
            "name": "Mẫn Nhi"
        },
        {
            "id": "666896678",
            "count": 0,
            "name": "Trần Thiên"
        },
        {
            "id": "100039603168929",
            "count": 0,
            "name": "Người dùng facebook"
        },
        {
            "id": "100016874224065",
            "count": 0,
            "name": "Người dùng facebook"
        },
        {
            "id": "100083174347639",
            "count": 0,
            "name": "Nguyễn Đức Bình✅"
        },
        {
            "id": "100071680238906",
            "count": 0,
            "name": "Người dùng facebook"
        },
        {
            "id": "100056903295591",
            "count": 0,
            "name": "Người dùng facebook"
        },
        {
            "id": "100023947532213",
            "count": 0,
            "name": "Người dùng facebook"
        },
        {
            "id": "100026180030782",
            "count": 0,
            "name": "Người dùng facebook"
        },
        {
            "id": "1550702797",
            "count": 0,
            "name": "Người dùng facebook"
        },
        {
            "id": "61563772222586",
            "count": 0,
            "name": "Người dùng facebook"
        },
        {
            "id": "61561974429884",
            "count": 0,
            "name": "Người dùng facebook"
        },
        {
            "id": "100076900489677",
            "count": 0,
            "name": "Lê Yến Nhi"
        },
        {
            "id": "100001283010247",
            "count": 0,
            "name": "Người dùng facebook"
        },
        {
            "id": "61559047337017",
            "count": 0,
            "name": "Người dùng facebook"
        },
        {
            "id": "100007621141247",
            "count": 0,
            "name": "Người dùng facebook"
        },
        {
            "id": "61564147886146",
            "count": 0,
            "name": "Người dùng facebook"
        },
        {
            "id": "1721994577",
            "count": 0,
            "name": "Người dùng facebook"
        },
        {
            "id": "100085462005868",
            "count": 0,
            "name": "Người dùng facebook"
        }
    ],
    "time": 2,
    "last": {
        "time": 4,
        "day": [
            {
                "id": "100071768980176",
                "count": 0
            },
            {
                "id": "100029340348630",
                "count": 0
            },
            {
                "id": "100078770982954",
                "count": 0
            },
            {
                "id": "100093012078559",
                "count": 0
            },
            {
                "id": "100028201899374",
                "count": 0
            },
            {
                "id": "100071216006358",
                "count": 0
            },
            {
                "id": "100089033040313",
                "count": 0
            },
            {
                "id": "100087986034465",
                "count": 0
            },
            {
                "id": "100088810007933",
                "count": 0
            },
            {
                "id": "100060845223319",
                "count": 0
            },
            {
                "id": "100080127415127",
                "count": 0
            },
            {
                "id": "100056967003808",
                "count": 0
            },
            {
                "id": "100090436251497",
                "count": 0
            },
            {
                "id": "61559179119012",
                "count": 0
            },
            {
                "id": "100062327635551",
                "count": 0
            },
            {
                "id": "61552955900740",
                "count": 0
            },
            {
                "id": "100086649001317",
                "count": 0
            },
            {
                "id": "100069227582339",
                "count": 0
            },
            {
                "id": "100005375501114",
                "count": 0
            },
            {
                "id": "100075683151810",
                "count": 0
            },
            {
                "id": "100029319195167",
                "count": 0
            },
            {
                "id": "100040542224086",
                "count": 0
            },
            {
                "id": "100078831493987",
                "count": 0
            },
            {
                "id": "100002486883891",
                "count": 0
            },
            {
                "id": "100089195796584",
                "count": 0
            },
            {
                "id": "100080101487002",
                "count": 0
            },
            {
                "id": "666896678",
                "count": 0
            },
            {
                "id": "100039603168929",
                "count": 0
            },
            {
                "id": "100016874224065",
                "count": 0
            },
            {
                "id": "100083174347639",
                "count": 0
            },
            {
                "id": "100071680238906",
                "count": 0
            },
            {
                "id": "100056903295591",
                "count": 0
            },
            {
                "id": "100023947532213",
                "count": 0
            },
            {
                "id": "100026180030782",
                "count": 0
            },
            {
                "id": "1550702797",
                "count": 0
            },
            {
                "id": "61563772222586",
                "count": 0
            },
            {
                "id": "61561974429884",
                "count": 0
            },
            {
                "id": "100076900489677",
                "count": 0
            },
            {
                "id": "100001283010247",
                "count": 0
            },
            {
                "id": "100007621141247",
                "count": 0
            },
            {
                "id": "61559047337017",
                "count": 0
            },
            {
                "id": "61564147886146",
                "count": 0
            },
            {
                "id": "1721994577",
                "count": 0
            },
            {
                "id": "100085462005868",
                "count": 0
            }
        ],
        "week": [
            {
                "id": "100071768980176",
                "count": 0
            },
            {
                "id": "100029340348630",
                "count": 0
            },
            {
                "id": "100078770982954",
                "count": 0
            },
            {
                "id": "100093012078559",
                "count": 0
            },
            {
                "id": "100028201899374",
                "count": 0
            },
            {
                "id": "100071216006358",
                "count": 0
            },
            {
                "id": "100089033040313",
                "count": 0
            },
            {
                "id": "100087986034465",
                "count": 0
            },
            {
                "id": "100088810007933",
                "count": 0
            },
            {
                "id": "100060845223319",
                "count": 0
            },
            {
                "id": "100080127415127",
                "count": 0
            },
            {
                "id": "100056967003808",
                "count": 0
            },
            {
                "id": "100090436251497",
                "count": 0
            },
            {
                "id": "61559179119012",
                "count": 0
            },
            {
                "id": "100062327635551",
                "count": 0
            },
            {
                "id": "61552955900740",
                "count": 0
            },
            {
                "id": "100086649001317",
                "count": 0
            },
            {
                "id": "100069227582339",
                "count": 0
            },
            {
                "id": "100005375501114",
                "count": 0
            },
            {
                "id": "100075683151810",
                "count": 0
            },
            {
                "id": "100029319195167",
                "count": 0
            },
            {
                "id": "100040542224086",
                "count": 0
            },
            {
                "id": "100078831493987",
                "count": 0
            },
            {
                "id": "100002486883891",
                "count": 0
            },
            {
                "id": "100089195796584",
                "count": 0
            },
            {
                "id": "100080101487002",
                "count": 0
            },
            {
                "id": "666896678",
                "count": 0
            },
            {
                "id": "100039603168929",
                "count": 0
            },
            {
                "id": "100016874224065",
                "count": 0
            },
            {
                "id": "100083174347639",
                "count": 0
            },
            {
                "id": "100071680238906",
                "count": 0
            },
            {
                "id": "100056903295591",
                "count": 0
            },
            {
                "id": "100023947532213",
                "count": 0
            },
            {
                "id": "100026180030782",
                "count": 0
            },
            {
                "id": "1550702797",
                "count": 0
            },
            {
                "id": "61563772222586",
                "count": 0
            },
            {
                "id": "61561974429884",
                "count": 0
            },
            {
                "id": "100076900489677",
                "count": 0
            },
            {
                "id": "100001283010247",
                "count": 0
            },
            {
                "id": "100007621141247",
                "count": 0
            },
            {
                "id": "61559047337017",
                "count": 0
            },
            {
                "id": "61564147886146",
                "count": 0
            },
            {
                "id": "1721994577",
                "count": 0
            },
            {
                "id": "100085462005868",
                "count": 0
            }
        ]
    }
}